{"type": "FeatureCollection", "features": [{"type":"Feature","geometry":{"type":"Point","coordinates":[-122.412153,37.78004]},"properties":{"cartodb_id":3,"name":"Lyle Tuttle's 1st Tattoo Shop","description":"Lyle opened up shop in 1960 at #30 7th St., in between Mission St. and Market St., also referred to as South of Market, San Francisco, CA. As the story goes, the end of an era and the beginning of a new one. Lyle tattooed at #30 7th St., San Francisco, CA. for 29 and a half years, until the Loma Prieta Earthquake in 1989 caused the building to be \"yellow tagged\".","created_at":"2015-04-17T21:04:11Z","updated_at":"2015-04-21T22:32:08Z","img_url1":"http://www.nuvo.net/imager/tuttles-san-francisco-tattooing-shop/b/original/2371579/f200/1320242326-7thst_copy.jpg","img_url1_src":"http://www.nuvo.net/indianapolis/spirit-and-place-tattoo-artist-lyle-tuttle/Content?oid=2371574","link_url1":"http://en.wikipedia.org/wiki/Lyle_Tuttle","latitude":37.78004,"longitude":-122.412153,"img_url2":null}},{"type":"Feature","geometry":{"type":"Point","coordinates":[-122.413472,37.802428]},"properties":{"cartodb_id":4,"name":"Lyle Tuttle's Tattoo Museum & Shop","description":"The shop and the museum are both now open at 841 Columbus Avenue.","created_at":"2015-04-17T21:33:29Z","updated_at":"2015-04-21T22:32:08Z","img_url1":"https://a2-images.myspacecdn.com/images02/86/f4e6dfed609548ab950980724fd3d47a/300x300.jpg","img_url1_src":"https://myspace.com/lyletuttle/photos","link_url1":"http://www.lyletuttle.com/","latitude":37.802428,"longitude":-122.413472,"img_url2":null}},{"type":"Feature","geometry":{"type":"Point","coordinates":[-122.418282,37.750532]},"properties":{"cartodb_id":5,"name":"Ed Hardy's 1st Tattoo City Location","description":"The first was at 2906 Mission Street in San Francisco, built by Ed in 1977. It was the first shop to open in the Mission district and featured the fine-line black & grey work that was new to the tattoo world at that time. This shop was destroyed in a fire in 1978, open less than a year but making an indelible mark on the Bay area walk-in tattoo shop scene. Some work done here is featured in the excellent documentary film “Tattoo City” by San Francisco filmmaker Emiko Omori, released in 1980.","created_at":"2015-04-20T00:21:03Z","updated_at":"2015-04-21T22:32:08Z","img_url1":"http://www.hardymarks.com/images/gallery/1970s/large/ORIGINAL_TATTOO_CITY_CARD_1977.jpg","img_url1_src":"http://www.hardymarks.com/deh/gallery/1970s/","link_url1":"http://www.tattoocitysf.com/history.html","latitude":37.750532,"longitude":-122.418282,"img_url2":null}},{"type":"Feature","geometry":{"type":"Point","coordinates":[-122.413204,37.802934]},"properties":{"cartodb_id":7,"name":"Tattoo City (Modern Location)","description":"Tattoo City continues to uphold the same standard of excellence and trend-setting qualities that have characterized Ed Hardy’s career. His more than forty years’ professional experience as an artist, spokesman, historian and documentarian of tattooing underlies every job produced at Tattoo City. With our fresh interpretations of world art traditions, we offer work that is truly “Way out but classic”.","created_at":"2015-04-21T22:28:08Z","updated_at":"2015-04-21T22:32:08Z","img_url1":"http://www.tattoocitysf.com/wp-content/uploads/2012/12/shopfront.jpg","img_url1_src":"http://www.tattoocitysf.com/#navanch22","link_url1":"http://www.tattoocitysf.com/#navanch22","latitude":37.802934,"longitude":-122.413204,"img_url2":null}}]}